.dir-locals.el
.gitignore
.hgignore
.hgtags
.readthedocs.yaml
Changes.rst
LICENSE
README.rst
checkpatch.py
pyproject.toml
setup.cfg
setup.py
.github/workflows/test.yml
Include/fuse_common.pxd
Include/fuse_lowlevel.pxd
Include/fuse_opt.pxd
Include/pthread.pxd
Include/libc/__init__.py
Include/libc/dirent.pxd
Include/libc/sys/__init__.py
Include/libc/sys/statvfs.pxd
developer-notes/FUSEError Performance.html
developer-notes/FUSEError Performance.ipynb
developer-notes/Namedtuple.html
developer-notes/Namedtuple.ipynb
developer-notes/lookup_counts.rst
developer-notes/release-process.md
doc/.placeholder
doc/html/.buildinfo
doc/html/about.html
doc/html/changes.html
doc/html/data.html
doc/html/example.html
doc/html/fuse_api.html
doc/html/general.html
doc/html/genindex.html
doc/html/gotchas.html
doc/html/index.html
doc/html/install.html
doc/html/lock.html
doc/html/objects.inv
doc/html/operations.html
doc/html/py-modindex.html
doc/html/search.html
doc/html/searchindex.js
doc/html/util.html
doc/html/.doctrees/about.doctree
doc/html/.doctrees/changes.doctree
doc/html/.doctrees/data.doctree
doc/html/.doctrees/environment.pickle
doc/html/.doctrees/example.doctree
doc/html/.doctrees/fuse_api.doctree
doc/html/.doctrees/general.doctree
doc/html/.doctrees/gotchas.doctree
doc/html/.doctrees/index.doctree
doc/html/.doctrees/install.doctree
doc/html/.doctrees/lock.doctree
doc/html/.doctrees/operations.doctree
doc/html/.doctrees/util.doctree
doc/html/_sources/about.rst.txt
doc/html/_sources/changes.rst.txt
doc/html/_sources/data.rst.txt
doc/html/_sources/example.rst.txt
doc/html/_sources/fuse_api.rst.txt
doc/html/_sources/general.rst.txt
doc/html/_sources/gotchas.rst.txt
doc/html/_sources/index.rst.txt
doc/html/_sources/install.rst.txt
doc/html/_sources/lock.rst.txt
doc/html/_sources/operations.rst.txt
doc/html/_sources/util.rst.txt
doc/html/_static/basic.css
doc/html/_static/classic.css
doc/html/_static/default.css
doc/html/_static/doctools.js
doc/html/_static/documentation_options.js
src/llfuse.egg-info/PKG-INFO
src/llfuse.egg-info/SOURCES.txt
src/llfuse.egg-info/dependency_links.txt
src/llfuse.egg-info/top_level.txt
src/llfuse.egg-info/zip-safe
