Metadata-Version: 2.1
Name: llfuse
Version: 1.5.1
Summary: Python bindings for the low-level FUSE API
Home-page: https://github.com/python-llfuse/python-llfuse/
Author: Nikolaus Rath
Author-email: Nikolaus@rath.org
License: LGPL
Keywords: FUSE,python
Platform: Linux
Platform: FreeBSD
Platform: OS X
Classifier: Development Status :: 4 - Beta
Classifier: Intended Audience :: Developers
Classifier: Programming Language :: Python
Classifier: Programming Language :: Python :: 3
Classifier: Programming Language :: Python :: 3.8
Classifier: Programming Language :: Python :: 3.9
Classifier: Programming Language :: Python :: 3.10
Classifier: Programming Language :: Python :: 3.11
Classifier: Programming Language :: Python :: 3.12
Classifier: Programming Language :: Python :: 3.13
Classifier: Topic :: Software Development :: Libraries :: Python Modules
Classifier: Topic :: System :: Filesystems
Classifier: License :: OSI Approved :: GNU Library or Lesser General Public License (LGPL)
Classifier: Operating System :: POSIX :: Linux
Classifier: Operating System :: MacOS :: MacOS X
Classifier: Operating System :: POSIX :: BSD :: FreeBSD
Provides: llfuse
Requires-Python: >=3.8
License-File: LICENSE
